sketch/PencilSketch.py
sketch/__init__.py
PencilSketch-0.0.1.dist-info/LICENSE.txt
PencilSketch-0.0.1.dist-info/METADATA
PencilSketch-0.0.1.dist-info/WHEEL
PencilSketch-0.0.1.dist-info/top_level.txt
PencilSketch-0.0.1.dist-info/RECORD
