Metadata-Version: 2.1
Name: PencilSketch
Version: 0.0.1
Summary: PythonTutorial
Author: Shakthibala
Author-email: shakthibala2004@gmail.com
Keywords: python,tutorial,PencilSketch,Sketch,ImageSketch
Classifier: Development Status :: 1 - Planning
Classifier: Intended Audience :: Developers
Classifier: Programming Language :: Python :: 3
Classifier: Operating System :: Unix
Classifier: Operating System :: MacOS :: MacOS X
Classifier: Operating System :: Microsoft :: Windows
License-File: LICENSE.txt
Requires-Dist: imageio
Requires-Dist: matplotlib
Requires-Dist: numpy
Requires-Dist: scipy
